grugstore/__init__.py
grugstore-0.1.3.dist-info/METADATA
grugstore-0.1.3.dist-info/WHEEL
grugstore-0.1.3.dist-info/entry_points.txt
grugstore-0.1.3.dist-info/licenses/LICENSE
grugstore-0.1.3.dist-info/RECORD
