Metadata-Version: 2.4
Name: grugstore
Version: 0.1.3
Summary: Simplest possible content-addressable file store for blobs.
Project-URL: Homepage, https://github.com/jbn/grugstore
Project-URL: Repository, https://github.com/jbn/grugstore
Project-URL: Bug Tracker, https://github.com/jbn/grugstore/issues
Author-email: generativist <jbn@abreka.com>
License: MIT
License-File: LICENSE
Keywords: blob,content-addressable,file-store,storage
Classifier: Development Status :: 4 - Beta
Classifier: Intended Audience :: Developers
Classifier: License :: OSI Approved :: MIT License
Classifier: Operating System :: OS Independent
Classifier: Programming Language :: Python :: 3
Classifier: Programming Language :: Python :: 3.10
Classifier: Programming Language :: Python :: 3.11
Classifier: Programming Language :: Python :: 3.12
Classifier: Programming Language :: Python :: 3.13
Classifier: Topic :: Software Development :: Libraries :: Python Modules
Classifier: Topic :: System :: Filesystems
Requires-Python: >=3.10
Requires-Dist: base58>=2.1.1
